ArithematicCalc/__init__.py
ArithematicCalc/calc.py
ArithematicCalc-0.1.dist-info/LICENCE.txt
ArithematicCalc-0.1.dist-info/METADATA
ArithematicCalc-0.1.dist-info/WHEEL
ArithematicCalc-0.1.dist-info/top_level.txt
ArithematicCalc-0.1.dist-info/RECORD
