Metadata-Version: 2.1
Name: ArithematicCalc
Version: 0.1
Summary: A small example package
Author: Shubham Verma
Author-email: Shubham Verma <shubhamverma@ineuron.ai>
Project-URL: Homepage, https://github.com/Shubham3023/arithematiccalc
Classifier: Programming Language :: Python :: 3
Classifier: License :: OSI Approved :: MIT License
Classifier: Operating System :: OS Independent
Requires-Python: >=3.7
License-File: LICENCE.txt
